service_objects/__init__.py
service_objects/celery_services.py
service_objects/errors.py
service_objects/fields.py
service_objects/services.py
service_objects/views.py
django_service_objects-0.7.1.dist-info/LICENSE
django_service_objects-0.7.1.dist-info/METADATA
django_service_objects-0.7.1.dist-info/WHEEL
django_service_objects-0.7.1.dist-info/top_level.txt
django_service_objects-0.7.1.dist-info/RECORD
