Metadata-Version: 2.1
Name: django-service-objects
Version: 0.7.1
Summary: Service objects for Django
Home-page: https://github.com/mixxorz/django-service-objects
Author: Mitchel Cabuloy
Author-email: mixxorz@gmail.com
Maintainer: Mitchel Cabuloy
Maintainer-email: mixxorz@gmail.com
License: MIT License
Platform: UNKNOWN
Classifier: Development Status :: 4 - Beta
Classifier: Environment :: Plugins
Classifier: Environment :: Web Environment
Classifier: Intended Audience :: Developers
Classifier: License :: OSI Approved :: MIT License
Classifier: Operating System :: OS Independent
Classifier: Programming Language :: Python
Classifier: Programming Language :: Python :: 3
Classifier: Programming Language :: Python :: 3.7
Classifier: Programming Language :: Python :: 3.8
Classifier: Programming Language :: Python :: 3.9
Classifier: Programming Language :: Python :: 3.10
Classifier: Framework :: Django :: 2.2
Classifier: Framework :: Django :: 3.1
Classifier: Framework :: Django :: 3.2
Classifier: Framework :: Django :: 4.0
Classifier: Topic :: Internet :: WWW/HTTP
Classifier: Topic :: Internet :: WWW/HTTP :: Dynamic Content
License-File: LICENSE
Requires-Dist: Django (>=1.11)
Requires-Dist: six
Provides-Extra: celery
Requires-Dist: celery ; extra == 'celery'
